modernforms/__init__.py
modernforms/exceptions.py
modernforms/modernforms_fan.py
modernforms-0.1.6.dist-info/LICENSE
modernforms-0.1.6.dist-info/METADATA
modernforms-0.1.6.dist-info/WHEEL
modernforms-0.1.6.dist-info/top_level.txt
modernforms-0.1.6.dist-info/RECORD
