Metadata-Version: 2.1
Name: modernforms
Version: 0.1.6
Summary: An interface to control ModerForms smart fans
Home-page: https://github.com/quielb/pypi
Author: Barry Quiel
Author-email: barry.quiel@gmail.com
License: GPL
Platform: UNKNOWN
Classifier: License :: OSI Approved :: GNU General Public License v3 (GPLv3)
Classifier: Programming Language :: Python :: 3
Classifier: Operating System :: OS Independent
Requires-Dist: requests
